Workbook

Sheet 📋 Cover & Legend
B2: PASTA Threat Modeling — OT & IT Environments
B3: Process for Attack Simulation and Threat Analysis | Threat Register | Control Mitigations | Application Status Tracker
B5: PASTA Stage | C5: Stage Description | D5: Key Questions Answered
B6: Stage I – Business Objectives | C6: Define business objectives, compliance requirements, and risk appetite that shape the threat model scope | D6: What are we protecting and why? What regulatory mandates apply?
B7: Stage II – Technical Scope | C7: Enumerate the technical environment: assets, data flows, trust boundaries, and infrastructure components | D7: What is in scope? What are our attack surfaces?
B8: Stage III – App Decomposition | C8: Break down applications and systems into components, identify entry/exit points, data stores, and trust zones | D8: How does the system work? Where does data flow?
B9: Stage IV – Threat Analysis | C9: Identify relevant threat actors, threat scenarios, and attack vectors targeting the defined scope | D9: Who would attack us and how? What are the threat scenarios?
B10: Stage V – Vulnerability Analysis | C10: Map known vulnerabilities and weaknesses in assets against identified threats | D10: What weaknesses exist that threats can exploit?
B11: Stage VI – Attack Modeling | C11: Model specific attack paths using attack trees or kill chains to understand how threats materialize | D11: How exactly would an attacker exploit this? What is the kill chain?
B12: Stage VII – Risk & Impact Analysis | C12: Quantify and qualify risk based on likelihood and business impact; prioritize mitigations | D12: What is the business impact? What should we fix first?
B14: Application Status Colors | C14: Meaning | D14: Used In Sheet
B15: TRIGGERED + ALL CONTROLS IN PLACE | C15: Threat active — mitigations confirmed ✅ | D15: OT / IT / Shared Threat Sheets
B16: TRIGGERED + PARTIAL CONTROLS | C16: Threat active — some controls missing ⚠️ | D16: OT / IT / Shared Threat Sheets
B17: TRIGGERED + NO CONTROLS | C17: Threat active — UNMITIGATED ❌ | D17: OT / IT / Shared Threat Sheets
B18: NOT TRIGGERED | C18: No active threat detected | D18: OT / IT / Shared Threat Sheets
B21: Environment | C21: Description
B22: OT Environment | C22: Operational Technology: PLCs, RTUs, SCADA, HMIs, DCS, IEDs, field devices
B23: IT Environment | C23: Information Technology: Servers, workstations, cloud, networks, endpoints, applications
B24: Shared / Both | C24: Threats and controls applicable across OT and IT boundaries
B27: Column Guide — Threat Register Sheets
B28: Threat ID | C28: Unique identifier e.g. OT-IV-001 (Environment-Stage-Seq)
B29: PASTA Stage | C29: Which of the 7 PASTA stages this threat was identified in
B30: Threat Scenario | C30: Short descriptive name of the threat scenario
B31: Threat Description | C31: Detailed description: actor, attack vector, and business impact
B32: Target Asset | C32: The asset, component, data flow, or trust boundary being targeted
B33: Attack Vector | C33: Technical or physical mechanism of exploitation
B34: Threat Actor | C34: Likely actor: Nation-State / Cybercriminal / Insider / Hacktivist / Script Kiddie
B35: Likelihood (1-5) | C35: Probability of occurrence: 1=Very Low … 5=Very High
B36: Impact (1-5) | C36: Consequence severity: 1=Negligible … 5=Catastrophic
B37: Risk Score | C37: Likelihood × Impact (auto-calculated)
B38: Risk Level | C38: LOW / MEDIUM / HIGH / CRITICAL derived from Risk Score
B39: Control Mitigation | C39: Recommended security control(s) to mitigate the threat
... B45: Notes | C45: Additional context, residual risk, or remediation timeline

Sheet 📊 Risk Dashboard
B2: PASTA Threat Modeling — Risk Dashboard
B4: OT Environment — Threat Summary
B5: Metric | C5: CRITICAL | D5: HIGH | E5: MEDIUM | F5: LOW | G5: Total
B6: Threat Count | C6: =COUNTIF('🔴 OT Threats'!K4:K24,"CRITICAL") -> 6 | D6: =COUNTIF('🔴 OT Threats'!K4:K24,"HIGH") -> 15 | E6: =COUNTIF('🔴 OT Threats'!K4:K24,"MEDIUM") -> 0 | F6: =COUNTIF('🔴 OT Threats'!K4:K24,"LOW") -> 0 | G6: =COUNTA('🔴 OT Threats'!A4:A24) -> 21
B7: Triggered Threats | C7: =COUNTIFS('🔴 OT Threats'!K4:K24,"CRITICAL",'🔴 OT Threats'!P4:P24,"YES") -> 0 | D7: =COUNTIFS('🔴 OT Threats'!K4:K24,"HIGH",'🔴 OT Threats'!P4:P24,"YES") -> 0 | E7: =COUNTIFS('🔴 OT Threats'!K4:K24,"MEDIUM",'🔴 OT Threats'!P4:P24,"YES") -> 0 | F7: =COUNTIFS('🔴 OT Threats'!K4:K24,"LOW",'🔴 OT Threats'!P4:P24,"YES") -> 0 | G7: =COUNTIF('🔴 OT Threats'!P4:P24,"YES") -> 0
B8: Controls Implemented | C8: =COUNTIFS('🔴 OT Threats'!K4:K24,"CRITICAL",'🔴 OT Threats'!O4:O24,"Implemented") -> 0 | D8: =COUNTIFS('🔴 OT Threats'!K4:K24,"HIGH",'🔴 OT Threats'!O4:O24,"Implemented") -> 0 | E8: =COUNTIFS('🔴 OT Threats'!K4:K24,"MEDIUM",'🔴 OT Threats'!O4:O24,"Implemented") -> 0 | F8: =COUNTIFS('🔴 OT Threats'!K4:K24,"LOW",'🔴 OT Threats'!O4:O24,"Implemented") -> 0 | G8: =COUNTIF('🔴 OT Threats'!O4:O24,"Implemented") -> 0
B9: Unmitigated + Triggered | C9: =COUNTIFS('🔴 OT Threats'!K4:K24,"CRITICAL",'🔴 OT Threats'!P4:P24,"YES",'🔴 OT Threats'!O4:O24,"None") -> 0 | D9: =COUNTIFS('🔴 OT Threats'!K4:K24,"HIGH",'🔴 OT Threats'!P4:P24,"YES",'🔴 OT Threats'!O4:O24,"None") -> 0 | E9: =COUNTIFS('🔴 OT Threats'!K4:K24,"MEDIUM",'🔴 OT Threats'!P4:P24,"YES",'🔴 OT Threats'!O4:O24,"None") -> 0 | F9: =COUNTIFS('🔴 OT Threats'!K4:K24,"LOW",'🔴 OT Threats'!P4:P24,"YES",'🔴 OT Threats'!O4:O24,"None") -> 0 | G9: =COUNTIFS('🔴 OT Threats'!P4:P24,"YES",'🔴 OT Threats'!O4:O24,"None") -> 0
B11: IT Environment — Threat Summary
B12: Metric | C12: CRITICAL | D12: HIGH | E12: MEDIUM | F12: LOW | G12: Total
B13: Threat Count | C13: =COUNTIF('🟢 IT Threats'!K4:K22,"CRITICAL") -> 3 | D13: =COUNTIF('🟢 IT Threats'!K4:K22,"HIGH") -> 16 | E13: =COUNTIF('🟢 IT Threats'!K4:K22,"MEDIUM") -> 0 | F13: =COUNTIF('🟢 IT Threats'!K4:K22,"LOW") -> 0 | G13: =COUNTA('🟢 IT Threats'!A4:A22) -> 19
B14: Triggered Threats | C14: =COUNTIFS('🟢 IT Threats'!K4:K22,"CRITICAL",'🟢 IT Threats'!P4:P22,"YES") -> 0 | D14: =COUNTIFS('🟢 IT Threats'!K4:K22,"HIGH",'🟢 IT Threats'!P4:P22,"YES") -> 0 | E14: =COUNTIFS('🟢 IT Threats'!K4:K22,"MEDIUM",'🟢 IT Threats'!P4:P22,"YES") -> 0 | F14: =COUNTIFS('🟢 IT Threats'!K4:K22,"LOW",'🟢 IT Threats'!P4:P22,"YES") -> 0 | G14: =COUNTIF('🟢 IT Threats'!P4:P22,"YES") -> 0
B15: Controls Implemented | C15: =COUNTIFS('🟢 IT Threats'!K4:K22,"CRITICAL",'🟢 IT Threats'!O4:O22,"Implemented") -> 0 | D15: =COUNTIFS('🟢 IT Threats'!K4:K22,"HIGH",'🟢 IT Threats'!O4:O22,"Implemented") -> 0 | E15: =COUNTIFS('🟢 IT Threats'!K4:K22,"MEDIUM",'🟢 IT Threats'!O4:O22,"Implemented") -> 0 | F15: =COUNTIFS('🟢 IT Threats'!K4:K22,"LOW",'🟢 IT Threats'!O4:O22,"Implemented") -> 0 | G15: =COUNTIF('🟢 IT Threats'!O4:O22,"Implemented") -> 0
B16: Unmitigated + Triggered | C16: =COUNTIFS('🟢 IT Threats'!K4:K22,"CRITICAL",'🟢 IT Threats'!P4:P22,"YES",'🟢 IT Threats'!O4:O22,"None") -> 0 | D16: =COUNTIFS('🟢 IT Threats'!K4:K22,"HIGH",'🟢 IT Threats'!P4:P22,"YES",'🟢 IT Threats'!O4:O22,"None") -> 0 | E16: =COUNTIFS('🟢 IT Threats'!K4:K22,"MEDIUM",'🟢 IT Threats'!P4:P22,"YES",'🟢 IT Threats'!O4:O22,"None") -> 0 | F16: =COUNTIFS('🟢 IT Threats'!K4:K22,"LOW",'🟢 IT Threats'!P4:P22,"YES",'🟢 IT Threats'!O4:O22,"None") -> 0 | G16: =COUNTIFS('🟢 IT Threats'!P4:P22,"YES",'🟢 IT Threats'!O4:O22,"None") -> 0
B18: Shared — Threat Summary
B19: Metric | C19: CRITICAL | D19: HIGH | E19: MEDIUM | F19: LOW | G19: Total
B20: Threat Count | C20: =COUNTIF('🔵 Shared Threats'!K4:K13,"CRITICAL") -> 2 | D20: =COUNTIF('🔵 Shared Threats'!K4:K13,"HIGH") -> 8 | E20: =COUNTIF('🔵 Shared Threats'!K4:K13,"MEDIUM") -> 0 | F20: =COUNTIF('🔵 Shared Threats'!K4:K13,"LOW") -> 0 | G20: =COUNTA('🔵 Shared Threats'!A4:A13) -> 10
B21: Triggered Threats | C21: =COUNTIFS('🔵 Shared Threats'!K4:K13,"CRITICAL",'🔵 Shared Threats'!P4:P13,"YES") -> 0 | D21: =COUNTIFS('🔵 Shared Threats'!K4:K13,"HIGH",'🔵 Shared Threats'!P4:P13,"YES") -> 0 | E21: =COUNTIFS('🔵 Shared Threats'!K4:K13,"MEDIUM",'🔵 Shared Threats'!P4:P13,"YES") -> 0 | F21: =COUNTIFS('🔵 Shared Threats'!K4:K13,"LOW",'🔵 Shared Threats'!P4:P13,"YES") -> 0 | G21: =COUNTIF('🔵 Shared Threats'!P4:P13,"YES") -> 0
B22: Controls Implemented | C22: =COUNTIFS('🔵 Shared Threats'!K4:K13,"CRITICAL",'🔵 Shared Threats'!O4:O13,"Implemented") -> 0 | D22: =COUNTIFS('🔵 Shared Threats'!K4:K13,"HIGH",'🔵 Shared Threats'!O4:O13,"Implemented") -> 0 | E22: =COUNTIFS('🔵 Shared Threats'!K4:K13,"MEDIUM",'🔵 Shared Threats'!O4:O13,"Implemented") -> 0 | F22: =COUNTIFS('🔵 Shared Threats'!K4:K13,"LOW",'🔵 Shared Threats'!O4:O13,"Implemented") -> 0 | G22: =COUNTIF('🔵 Shared Threats'!O4:O13,"Implemented") -> 0
B23: Unmitigated + Triggered | C23: =COUNTIFS('🔵 Shared Threats'!K4:K13,"CRITICAL",'🔵 Shared Threats'!P4:P13,"YES",'🔵 Shared Threats'!O4:O13,"None") -> 0 | D23: =COUNTIFS('🔵 Shared Threats'!K4:K13,"HIGH",'🔵 Shared Threats'!P4:P13,"YES",'🔵 Shared Threats'!O4:O13,"None") -> 0 | E23: =COUNTIFS('🔵 Shared Threats'!K4:K13,"MEDIUM",'🔵 Shared Threats'!P4:P13,"YES",'🔵 Shared Threats'!O4:O13,"None") -> 0 | F23: =COUNTIFS('🔵 Shared Threats'!K4:K13,"LOW",'🔵 Shared Threats'!P4:P13,"YES",'🔵 Shared Threats'!O4:O13,"None") -> 0 | G23: =COUNTIFS('🔵 Shared Threats'!P4:P13,"YES",'🔵 Shared Threats'!O4:O13,"None") -> 0
B25: PASTA Stage Distribution (All Environments)
B26: PASTA Stage | C26: OT Count | D26: IT Count | E26: Shared Count | F26: Total
B27: Stage I – Business Objectives | C27: =COUNTIF('🔴 OT Threats'!B4:B24,"Stage I – Business Objectives") -> 2 | D27: =COUNTIF('🟢 IT Threats'!B4:B22,"Stage I – Business Objectives") -> 2 | E27: =COUNTIF('🔵 Shared Threats'!B4:B13,"Stage I – Business Objectives") -> 1 | F27: =SUM(C27:E27) -> 5
B28: Stage II – Technical Scope | C28: =COUNTIF('🔴 OT Threats'!B4:B24,"Stage II – Technical Scope") -> 3 | D28: =COUNTIF('🟢 IT Threats'!B4:B22,"Stage II – Technical Scope") -> 2 | E28: =COUNTIF('🔵 Shared Threats'!B4:B13,"Stage II – Technical Scope") -> 1 | F28: =SUM(C28:E28) -> 6
B29: Stage III – App Decomposition | C29: =COUNTIF('🔴 OT Threats'!B4:B24,"Stage III – App Decomposition") -> 3 | D29: =COUNTIF('🟢 IT Threats'!B4:B22,"Stage III – App Decomposition") -> 3 | E29: =COUNTIF('🔵 Shared Threats'!B4:B13,"Stage III – App Decomposition") -> 1 | F29: =SUM(C29:E29) -> 7
B30: Stage IV – Threat Analysis | C30: =COUNTIF('🔴 OT Threats'!B4:B24,"Stage IV – Threat Analysis") -> 4 | D30: =COUNTIF('🟢 IT Threats'!B4:B22,"Stage IV – Threat Analysis") -> 3 | E30: =COUNTIF('🔵 Shared Threats'!B4:B13,"Stage IV – Threat Analysis") -> 2 | F30: =SUM(C30:E30) -> 9
B31: Stage V – Vulnerability Analysis | C31: =COUNTIF('🔴 OT Threats'!B4:B24,"Stage V – Vulnerability Analysis") -> 3 | D31: =COUNTIF('🟢 IT Threats'!B4:B22,"Stage V – Vulnerability Analysis") -> 3 | E31: =COUNTIF('🔵 Shared Threats'!B4:B13,"Stage V – Vulnerability Analysis") -> 1 | F31: =SUM(C31:E31) -> 7
B32: Stage VI – Attack Modeling | C32: =COUNTIF('🔴 OT Threats'!B4:B24,"Stage VI – Attack Modeling") -> 3 | D32: =COUNTIF('🟢 IT Threats'!B4:B22,"Stage VI – Attack Modeling") -> 3 | E32: =COUNTIF('🔵 Shared Threats'!B4:B13,"Stage VI – Attack Modeling") -> 2 | F32: =SUM(C32:E32) -> 8
B33: Stage VII – Risk & Impact Analysis | C33: =COUNTIF('🔴 OT Threats'!B4:B24,"Stage VII – Risk & Impact Analysis") -> 3 | D33: =COUNTIF('🟢 IT Threats'!B4:B22,"Stage VII – Risk & Impact Analysis") -> 3 | E33: =COUNTIF('🔵 Shared Threats'!B4:B13,"Stage VII – Risk & Impact Analysis") -> 2 | F33: =SUM(C33:E33) -> 8
B35: 🤖 APPLICATION INTEGRATION: Set 'Threat Triggered?' = YES and 'Control Status' = None/Partial/Implemented in each threat sheet. 'App Status' column (Q) and Dashboard counters update automatically.

Sheet 🔴 OT Threats
A2: PASTA Threat Register — 🔴 OT Threats
A3: Threat ID | B3: PASTA Stage | C3: Threat Scenario | D3: Threat Description | E3: Target Asset | F3: Attack Vector | G3: Threat Actor | H3: Likelihood (1-5) | I3: Impact (1-5) | J3: Risk Score | K3: Risk Level | L3: Control Mitigation | M3: Control Standard Ref | N3: Attack Pattern (CAPEC) | O3: Control Status | P3: Threat Triggered? | Q3: App Status | R3: Notes
A4: OT-I-001 | B4: Stage I – Business Objectives | C4: Regulatory Non-Compliance Exploitation | D4: Attacker targets known compliance gaps in NERC CIP or IEC 62443 programs to exploit unprotected critical cyber assets that regulators have not yet flagged | E4: Critical Cyber Assets / CIP Program | F4: Exploitation of audit scope exclusions or CIP categorization gaps | G4: Nation-State / Cybercriminal | H4: 4 | I4: 4 | J4: 16 | K4: HIGH | L4: Annual CIP asset categorization review; threat-informed compliance program; internal audits beyond minimum regulatory scope | M4: NERC CIP-002 / IEC 62443-2-1 | N4: CAPEC-169 | O4: None | P4: NO | Q4: =IF(P4="YES",IF(O4="Implemented","✅ Triggered+Mitigated",IF(O4="Partial","⚠️ Partial Controls","❌ Unmitigated")),"— Not Triggered") -> — Not Triggered | R4: Compliance scope gaps are a known blind spot in critical infrastructure protection
A5: OT-I-002 | B5: Stage I – Business Objectives | C5: Safety Case Integrity Attack | D5: Adversary targets documented safety cases and functional safety assessments to understand system limitations and design attacks that cause injury or environmental damage while bypassing safety systems | E5: Safety Case Documentation / SIS Design | F5: Document theft followed by targeted SIS manipulation | G5: Nation-State / Insider | H5: 2 | I5: 5 | J5: 10 | K5: HIGH | L5: Classify safety case documents; restrict access to SIL assessments; physical security for safety documentation; independent SIS verification | M5: IEC 61511 / IEC 62443-2-1 | N5: CAPEC-116 | O5: None | P5: NO | Q5: =IF(P5="YES",IF(O5="Implemented","✅ Triggered+Mitigated",IF(O5="Partial","⚠️ Partial Controls","❌ Unmitigated")),"— Not Triggered") -> — Not Triggered | R5: Safety case documents provide a roadmap for physical attacks through cyber means
A6: OT-II-003 | B6: Stage II – Technical Scope | C6: Asset Inventory Gap Exploitation | D6: Attacker leverages unknown or unmanaged OT assets (shadow devices, legacy PLCs) that fall outside the security monitoring scope to establish persistent footholds | E6: Unmanaged / Shadow OT Devices | F6: Network discovery of unmonitored assets followed by targeted exploitation | G6: Cybercriminal / Nation-State | H6: 4 | I6: 4 | J6: 16 | K6: HIGH | L6: Passive OT asset discovery (Dragos, Claroty, Nozomi); automated asset inventory; network access control for unauthorized devices; regular asset reconciliation | M6: IEC 62443-2-1 / NIST SP 800-82 | N6: CAPEC-309 | O6: None | P6: NO | Q6: =IF(P6="YES",IF(O6="Implemented","✅ Triggered+Mitigated",IF(O6="Partial","⚠️ Partial Controls","❌ Unmitigated")),"— Not Triggered") -> — Not Triggered | R6: OT asset inventories are routinely 30-50% incomplete in brownfield environments
A7: OT-II-004 | B7: Stage II – Technical Scope | C7: Trust Boundary Violation via DMZ Misconfiguration | D7: Attacker pivots from IT to OT by exploiting a misconfigured or overly permissive rule in the IT/OT DMZ firewall, violating the intended trust boundary | E7: IT/OT DMZ / Firewall | F7: Firewall rule exploitation; protocol tunneling through allowed ports | G7: Cybercriminal / Nation-State | H7: 4 | I7: 5 | J7: 20 | K7: CRITICAL | L7: Firewall rule base audit; deny-all default with explicit allow; data diodes for one-way feeds; quarterly DMZ penetration testing; network traffic analysis | M7: IEC 62443-3-3 SR 5.1 / NIST SP 800-82 | N7: CAPEC-122 | O7: None | P7: NO | Q7: =IF(P7="YES",IF(O7="Implemented","✅ Triggered+Mitigated",IF(O7="Partial","⚠️ Partial Controls","❌ Unmitigated")),"— Not Triggered") -> — Not Triggered | R7: Firewall misconfigurations are the most common IT-to-OT lateral movement enabler
A8: OT-II-005 | B8: Stage II – Technical Scope | C8: Remote Access Surface Exploitation | D8: Attacker exploits exposed remote access points (VPN, RDP, vendor jump servers) to the OT network that were enabled for operational necessity but inadequately secured | E8: Remote Access Gateway / VPN | F8: Credential stuffing; VPN vulnerability exploitation; vendor credential theft | G8: Cybercriminal / Nation-State | H8: 4 | I8: 5 | J8: 20 | K8: CRITICAL | L8: MFA on all remote access; JIT/JEA vendor access; session recording; disable persistent vendor connections; OT-specific VPN with strict ACLs | M8: IEC 62443-2-4 / NERC CIP-005 | N8: CAPEC-50 | O8: None | P8: NO | Q8: =IF(P8="YES",IF(O8="Implemented","✅ Triggered+Mitigated",IF(O8="Partial","⚠️ Partial Controls","❌ Unmitigated")),"— Not Triggered") -> — Not Triggered | R8: Verizon DBIR: remote access is the #1 OT initial access vector
A9: OT-III-006 | B9: Stage III – App Decomposition | C9: Data Flow Interception between SCADA and Field Devices | D9: Attacker intercepts unencrypted data flows between SCADA master and field RTUs/PLCs to capture process values, inject false data, or replay commands | E9: SCADA-to-Field Data Flows | F9: Man-in-the-Middle on OT LAN; ARP poisoning; protocol replay | G9: Nation-State / Insider | H9: 3 | I9: 5 | J9: 15 | K9: HIGH | L9: OT-aware IDS monitoring data flows; authenticated protocol variants (DNP3 SA); network encryption where supported; strict VLAN segmentation limiting flow exposure | M9: IEC 62443-3-3 SR 3.2 / IEC 62351 | N9: CAPEC-94 | O9: None | P9: NO | Q9: =IF(P9="YES",IF(O9="Implemented","✅ Triggered+Mitigated",IF(O9="Partial","⚠️ Partial Controls","❌ Unmitigated")),"— Not Triggered") -> — Not Triggered | R9: Legacy protocols lack authentication — detection is the primary compensating control
A10: OT-III-007 | B10: Stage III – App Decomposition | C10: HMI Entry Point Compromise | D10: Attacker uses the HMI as a decomposition entry point — it aggregates data from all PLCs and provides write access, making it the highest-value target in the control architecture | E10: HMI Workstation / SCADA Client | F10: Spear-phishing operator; removable media; vulnerable HMI software exploitation | G10: Cybercriminal / Insider | H10: 4 | I10: 5 | J10: 20 | K10: CRITICAL | L10: Application whitelisting on HMI; disable USB ports; patch HMI software; network isolation of HMI VLAN; role-based access for HMI functions | M10: IEC 62443-3-3 SR 2.4 / NIST SP 800-82 | N10: CAPEC-86 | O10: None | P10: NO | Q10: =IF(P10="YES",IF(O10="Implemented","✅ Triggered+Mitigated",IF(O10="Partial","⚠️ Partial Controls","❌ Unmitigated")),"— Not Triggered") -> — Not Triggered | R10: HMI compromise provides immediate process visibility and control capability to attacker
A11: OT-III-008 | B11: Stage III – App Decomposition | C11: Historian Replication Channel Abuse | D11: Attacker abuses the historian replication data flow between OT and IT zones — a necessary business connection — to pivot into OT or exfiltrate sensitive process data | E11: Process Historian / Replication Channel | F11: Exploitation of historian connector software; credential theft for replication account | G11: Cybercriminal / Nation-State | H11: 3 | I11: 4 | J11: 12 | K11: HIGH | L11: Unidirectional data diode or firewall on historian replication; dedicated replication service account with minimal privileges; encrypt historian replication traffic | M11: IEC 62443-3-3 SR 5.2 / NIST SP 800-82 | N11: CAPEC-188 | O11: None | P11: NO | Q11: =IF(P11="YES",IF(O11="Implemented","✅ Triggered+Mitigated",IF(O11="Partial","⚠️ Partial Controls","❌ Unmitigated")),"— Not Triggered") -> — Not Triggered | R11: Historian replication is a common IT/OT boundary crossing — must be hardened
A12: OT-IV-009 | B12: Stage IV – Threat Analysis | C12: Nation-State ICS-Specific Malware Deployment | D12: Nation-state actor deploys ICS-specific malware (Industroyer, TRITON/TRISIS, Pipedream) targeting PLCs, safety controllers, or protection relays to cause physical damage or safety incidents | E12: PLC / Safety Controller / Protection Relay | F12: Spear-phishing → lateral movement → OT-specific payload deployment | G12: Nation-State | H12: 2 | I12: 5 | J12: 10 | K12: HIGH | L12: OT threat intelligence feeds; network behavioral analytics; ICS-specific malware detection (Dragos/Claroty); safety system isolation; incident response retainer with ICS expertise | M12: IEC 62443-3-3 / NERC CIP-007 | N12: CAPEC-439 | O12: None | P12: NO | Q12: =IF(P12="YES",IF(O12="Implemented","✅ Triggered+Mitigated",IF(O12="Partial","⚠️ Partial Controls","❌ Unmitigated")),"— Not Triggered") -> — Not Triggered | R12: TRITON targeted Safety Instrumented Systems; Pipedream designed for broad ICS impact
A13: OT-IV-010 | B13: Stage IV – Threat Analysis | C13: Insider Sabotage of Process Control | D13: Disgruntled or coerced insider with engineering access intentionally misconfigures PLC setpoints, alarm limits, or interlocks to cause process upsets or equipment damage | E13: PLC / DCS / Safety Setpoints | F13: Direct engineering workstation access; abuse of legitimate credentials | G13: Insider | H13: 3 | I13: 5 | J13: 15 | K13: HIGH | L13: Dual-person authorization for critical setpoint changes; behavioral monitoring of engineering workstations; change management controls; separation of duties for safety parameters | M13: IEC 62443-2-1 / IEC 61511 | N13: CAPEC-122 | O13: None | P13: NO | Q13: =IF(P13="YES",IF(O13="Implemented","✅ Triggered+Mitigated",IF(O13="Partial","⚠️ Partial Controls","❌ Unmitigated")),"— Not Triggered") -> — Not Triggered | R13: Insider sabotage is underreported; operational culture and HR controls are as important as technical controls
A14: OT-IV-011 | B14: Stage IV – Threat Analysis | C14: Supply Chain Hardware Implant | D14: Compromised hardware component (PLC, switch, relay) delivered through the supply chain with embedded malicious firmware or hardware implant enabling persistent covert access | E14: Hardware Supply Chain / Field Devices | F14: Counterfeit or tampered hardware insertion during procurement or maintenance | G14: Nation-State | H14: 2 | I14: 5 | J14: 10 | K14: HIGH | L14: Hardware vendor vetting program; firmware hash verification on receipt; tamper-evident packaging; hardware security modules for critical devices | M14: NIST SP 800-161 / IEC 62443-2-4 | N14: CAPEC-439 | O14: None | P14: NO | Q14: =IF(P14="YES",IF(O14="Implemented","✅ Triggered+Mitigated",IF(O14="Partial","⚠️ Partial Controls","❌ Unmitigated")),"— Not Triggered") -> — Not Triggered | R14: Bloomberg 'Big Hack' highlighted hardware supply chain risk; extremely difficult to detect
A15: OT-IV-012 | B15: Stage IV – Threat Analysis | C15: Watering Hole Attack Targeting OT Vendors | D15: Attacker compromises a website frequently visited by OT engineers (vendor portal, ICS forum) to deliver targeted exploits against engineering workstation browsers | E15: Engineering Workstations / OT Staff | F15: Compromised vendor website; malicious download masquerading as firmware update | G15: Nation-State / Cybercriminal | H15: 3 | I15: 4 | J15: 12 | K15: HIGH | L15: Web proxy filtering on EWS; browser isolation; restrict engineering workstation internet access; OT-specific threat intelligence | M15: IEC 62443-2-1 / NIST SP 800-82 | N15: CAPEC-86 | O15: None | P15: NO | Q15: =IF(P15="YES",IF(O15="Implemented","✅ Triggered+Mitigated",IF(O15="Partial","⚠️ Partial Controls","❌ Unmitigated")),"— Not Triggered") -> — Not Triggered | R15: Engineering workstations are high-value targets with direct PLC programming access
... A24: OT-VII-021 | B24: Stage VII – Risk & Impact Analysis | C24: Extended Grid Outage via Coordinated Substation Attack | D24: Coordinated cyber attack on multiple substations (Industroyer/Crashoverride model) causes simultaneous protection relay misoperation, resulting in extended regional power outage | E24: Substation Protection Relays / EMS | F24: IEC 61850 GOOSE message injection; protection relay firmware attack; SCADA command spoofing | G24: Nation-State | H24: 2 | I24: 5 | J24: 10 | K24: HIGH | L24: Defense-in-depth for substation automation; IEC 62351 for substation communication security; network segmentation per substation; manual fallback procedures; NERC CIP enforcement | M24: NERC CIP-014 / IEC 62351 | N24: CAPEC-188 | O24: None | P24: NO | Q24: =IF(P24="YES",IF(O24="Implemented","✅ Triggered+Mitigated",IF(O24="Partial","⚠️ Partial Controls","❌ Unmitigated")),"— Not Triggered") -> — Not Triggered | R24: Ukraine 2015/2016 grid attacks demonstrated this scenario; recovery required manual re-energization

Sheet 🟢 IT Threats
A2: PASTA Threat Register — 🟢 IT Threats
A3: Threat ID | B3: PASTA Stage | C3: Threat Scenario | D3: Threat Description | E3: Target Asset | F3: Attack Vector | G3: Threat Actor | H3: Likelihood (1-5) | I3: Impact (1-5) | J3: Risk Score | K3: Risk Level | L3: Control Mitigation | M3: Control Standard Ref | N3: Attack Pattern (CAPEC) | O3: Control Status | P3: Threat Triggered? | Q3: App Status | R3: Notes
A4: IT-I-001 | B4: Stage I – Business Objectives | C4: Business-Motivated Data Theft for Competitive Advantage | D4: Attacker targets corporate intellectual property (R&D, product designs, M&A plans) aligned with specific business objectives that have identifiable economic value to nation-state or competitor | E4: Intellectual Property / Corporate Data | F4: Spear-phishing executives; cloud storage exfiltration; insider recruitment | G4: Nation-State / Cybercriminal | H4: 3 | I4: 4 | J4: 12 | K4: HIGH | L4: Data classification and DLP; UEBA for anomalous data access; email security with executive protection; IP access auditing; insider threat program | M4: NIST SP 800-53 AC-4 / CIS Control 3 | N4: CAPEC-167 | O4: None | P4: NO | Q4: =IF(P4="YES",IF(O4="Implemented","✅ Triggered+Mitigated",IF(O4="Partial","⚠️ Partial Controls","❌ Unmitigated")),"— Not Triggered") -> — Not Triggered | R4: Economic espionage targets align with national strategic priorities — threat-informed approach required
A5: IT-I-002 | B5: Stage I – Business Objectives | C5: Ransomware Business Disruption for Financial Gain | D5: Organized criminal group deploys ransomware targeting business-critical IT systems to extort payment, with double-extortion exfiltration ensuring leverage even with backups | E5: IT Infrastructure / Business Operations | F5: Phishing → initial access broker → lateral movement → ransomware deployment | G5: Cybercriminal | H5: 5 | I5: 5 | J5: 25 | K5: CRITICAL | L5: Offline immutable backups; EDR with rollback; network segmentation; IR retainer; tested DR plan; cyber insurance; employee security awareness | M5: NIST CSF RC.RP-1 / CIS Control 11 | N5: CAPEC-549 | O5: None | P5: NO | Q5: =IF(P5="YES",IF(O5="Implemented","✅ Triggered+Mitigated",IF(O5="Partial","⚠️ Partial Controls","❌ Unmitigated")),"— Not Triggered") -> — Not Triggered | R5: Average ransomware recovery cost exceeds $1.8M (Sophos 2024); prevention and recovery planning equally important
A6: IT-II-003 | B6: Stage II – Technical Scope | C6: Cloud Shadow IT Attack Surface | D6: Business units deploy unauthorized cloud services outside security team visibility, creating unmonitored attack surface with misconfigurations and inadequate security controls | E6: Shadow Cloud Services / SaaS | F6: Exploitation of misconfigured public-facing shadow IT resources | G6: Cybercriminal / Nation-State | H6: 4 | I6: 3 | J6: 12 | K6: HIGH | L6: Cloud Access Security Broker (CASB); DNS monitoring for unknown SaaS; Cloud Security Posture Management; approved cloud service catalog; automated shadow IT discovery | M6: NIST CSF ID.AM-3 / CIS Control 1 | N6: CAPEC-212 | O6: None | P6: NO | Q6: =IF(P6="YES",IF(O6="Implemented","✅ Triggered+Mitigated",IF(O6="Partial","⚠️ Partial Controls","❌ Unmitigated")),"— Not Triggered") -> — Not Triggered | R6: Shadow IT is endemic — CASB and DNS monitoring are the most effective detection approaches
A7: IT-II-004 | B7: Stage II – Technical Scope | C7: Internet-Exposed Management Interfaces | D7: Attacker discovers and exploits internet-exposed administrative interfaces (RDP, SSH, Citrix, VPN, admin portals) that are accessible without adequate authentication controls | E7: Internet-Facing Management Interfaces | F7: Shodan/Censys reconnaissance; credential brute-force; vulnerability exploitation | G7: Cybercriminal / Nation-State | H7: 5 | I7: 4 | J7: 20 | K7: CRITICAL | L7: External attack surface management (ASM) tool; restrict management interfaces to VPN/private network only; MFA on all remote management; automated internet exposure monitoring | M7: NIST CSF PR.AC-3 / CIS Control 12 | N7: CAPEC-48 | O7: None | P7: NO | Q7: =IF(P7="YES",IF(O7="Implemented","✅ Triggered+Mitigated",IF(O7="Partial","⚠️ Partial Controls","❌ Unmitigated")),"— Not Triggered") -> — Not Triggered | R7: Shodan exposes thousands of corporate RDP/SSH interfaces; external ASM is a foundational capability
A8: IT-III-005 | B8: Stage III – App Decomposition | C8: API Gateway Logic Bypass | D8: Attacker identifies and exploits API endpoints that bypass the gateway through direct backend access, circumventing authentication, rate limiting, and input validation controls | E8: API Gateway / Backend Services | F8: Direct backend API access; IDOR; JWT manipulation; API versioning abuse | G8: Cybercriminal | H8: 3 | I8: 4 | J8: 12 | K8: HIGH | L8: Enforce API gateway for all backend access; network policy blocking direct backend access; API security testing (OWASP API Top 10); JWT validation hardening | M8: OWASP API Top 10 / NIST SP 800-53 SC-8 | N8: CAPEC-110 | O8: None | P8: NO | Q8: =IF(P8="YES",IF(O8="Implemented","✅ Triggered+Mitigated",IF(O8="Partial","⚠️ Partial Controls","❌ Unmitigated")),"— Not Triggered") -> — Not Triggered | R8: OWASP API Security Top 10 documents systematic API decomposition attack patterns
A9: IT-III-006 | B9: Stage III – App Decomposition | C9: Authentication Service Single Point of Failure Attack | D9: Attacker targets the identity provider (AD, SAML IDP, OAuth server) as a high-value decomposition target — compromise yields access to all dependent applications | E9: Active Directory / Identity Provider | F9: Golden Ticket; DCSync; SAML token forgery; IDP admin compromise | G9: Nation-State / Cybercriminal | H9: 3 | I9: 5 | J9: 15 | K9: HIGH | L9: AD tiering model; protect IDP with hardware MFA; monitor DCSync events; IDP hardening (MDE for Identity); break-glass account procedures | M9: NIST SP 800-63C / CIS Control 5 | N9: CAPEC-194 | O9: None | P9: NO | Q9: =IF(P9="YES",IF(O9="Implemented","✅ Triggered+Mitigated",IF(O9="Partial","⚠️ Partial Controls","❌ Unmitigated")),"— Not Triggered") -> — Not Triggered | R9: Identity provider compromise is game-over for all federated applications — highest priority hardening target
A10: IT-III-007 | B10: Stage III – App Decomposition | C10: Microservice Trust Exploitation | D10: Attacker compromises one microservice and exploits implicit trust between microservices (missing mTLS, overpermissive service accounts) to laterally move across the application | E10: Microservices / Service Mesh | F10: Service account token theft; internal API exploitation; SSRF to metadata service | G10: Cybercriminal / Nation-State | H10: 3 | I10: 4 | J10: 12 | K10: HIGH | L10: Mutual TLS (mTLS) between all services; service mesh (Istio/Linkerd); least-privilege service accounts; zero-trust microsegmentation; SSRF protections | M10: NIST SP 800-204 / CIS Control 14 | N10: CAPEC-122 | O10: None | P10: NO | Q10: =IF(P10="YES",IF(O10="Implemented","✅ Triggered+Mitigated",IF(O10="Partial","⚠️ Partial Controls","❌ Unmitigated")),"— Not Triggered") -> — Not Triggered | R10: Microservice architectures assume internal trust by default — explicitly deny and authenticate all service-to-service calls
A11: IT-IV-008 | B11: Stage IV – Threat Analysis | C11: Advanced Persistent Threat Dwell Time Exploitation | D11: Nation-state APT establishes persistent access in corporate IT network and spends months performing reconnaissance, data exfiltration, and capability staging before being detected | E11: IT Network / Corporate Systems | F11: Living-off-the-land; LOLBins; encrypted C2 channels; legitimate tool abuse | G11: Nation-State | H11: 3 | I11: 4 | J11: 12 | K11: HIGH | L11: Threat hunting program; behavioral analytics (UEBA/EDR); network traffic analysis; 90-day log retention minimum; purple team exercises; threat intelligence integration | M11: NIST SP 800-61 / MITRE ATT&CK | N11: CAPEC-167 | O11: None | P11: NO | Q11: =IF(P11="YES",IF(O11="Implemented","✅ Triggered+Mitigated",IF(O11="Partial","⚠️ Partial Controls","❌ Unmitigated")),"— Not Triggered") -> — Not Triggered | R11: Average APT dwell time historically >200 days before detection; proactive hunting essential
A12: IT-IV-009 | B12: Stage IV – Threat Analysis | C12: Insider Threat — Privileged Data Exfiltration | D12: Malicious insider with privileged access to sensitive systems systematically exfiltrates customer data, credentials, or IP before resignation or under external coercion | E12: Privileged Systems / Sensitive Data | F12: Legitimate access abuse; bulk data export; encrypted personal cloud sync | G12: Insider | H12: 3 | I12: 5 | J12: 15 | K12: HIGH | L12: UEBA with insider threat detection; DLP with user attribution; screen recording for privileged sessions; data access auditing; offboarding checklist; background screening | M12: NIST SP 800-53 AC-2 / CIS Control 8 | N12: CAPEC-122 | O12: None | P12: NO | Q12: =IF(P12="YES",IF(O12="Implemented","✅ Triggered+Mitigated",IF(O12="Partial","⚠️ Partial Controls","❌ Unmitigated")),"— Not Triggered") -> — Not Triggered | R12: Insider threats cause 34% of breaches (Verizon DBIR) — hardest to detect with purely technical controls
A13: IT-IV-010 | B13: Stage IV – Threat Analysis | C13: Business Email Compromise Targeting Finance | D13: Attacker compromises executive or finance email account (or creates convincing look-alike domain) to authorize fraudulent wire transfers or manipulate financial processes | E13: Email / Finance Systems | F13: Executive email compromise; CEO impersonation; invoice fraud | G13: Cybercriminal | H13: 4 | I13: 4 | J13: 16 | K13: HIGH | L13: MFA on all email accounts; DMARC/DKIM/SPF enforcement; out-of-band wire transfer verification; financial transaction anomaly detection; executive email domain monitoring | M13: NIST SP 800-53 SI-12 / CIS Control 6 | N13: CAPEC-98 | O13: None | P13: NO | Q13: =IF(P13="YES",IF(O13="Implemented","✅ Triggered+Mitigated",IF(O13="Partial","⚠️ Partial Controls","❌ Unmitigated")),"— Not Triggered") -> — Not Triggered | R13: BEC losses exceed $2.9B annually (FBI IC3); most effective defense is out-of-band verification
A14: IT-V-011 | B14: Stage V – Vulnerability Analysis | C14: Unpatched Critical Vulnerability Exploitation (N-Day) | D14: Attacker exploits a known critical CVE (CVSS 9+) in internet-facing or internal systems that has not been patched within the organization's patching SLA, enabling initial access or privilege escalation | E14: Internet-Facing / Internal Systems | F14: Public exploit code execution against unpatched vulnerability | G14: Cybercriminal / Nation-State | H14: 4 | I14: 4 | J14: 16 | K14: HIGH | L14: Vulnerability management with <30-day SLA for critical; continuous scanning; prioritization by exploitability (EPSS); compensating controls while patching; patch exception process | M14: NIST SP 800-53 SI-2 / CIS Control 7 | N14: CAPEC-66 | O14: None | P14: NO | Q14: =IF(P14="YES",IF(O14="Implemented","✅ Triggered+Mitigated",IF(O14="Partial","⚠️ Partial Controls","❌ Unmitigated")),"— Not Triggered") -> — Not Triggered | R14: ExploitDB and Metasploit make n-day exploitation trivial; patch velocity is the key metric
A15: IT-V-012 | B15: Stage V – Vulnerability Analysis | C15: Misconfigured Cloud IAM Privilege Escalation Path | D15: Security assessment reveals privilege escalation paths through misconfigured IAM policies, resource-based policies, or trust relationships that allow a low-privilege user to achieve admin access | E15: Cloud IAM / Resource Policies | F15: IAM policy exploitation; assume-role chaining; resource-based policy abuse | G15: Cybercriminal / Insider | H15: 3 | I15: 4 | J15: 12 | K15: HIGH | L15: IAM Access Analyzer; Cloudsplaining/PMapper for IAM analysis; least-privilege IAM; SCPs as guardrails; Privileged Identity Management with JIT elevation | M15: CIS AWS/Azure Benchmark / NIST CSF PR.AC-4 | N15: CAPEC-122 | O15: None | P15: NO | Q15: =IF(P15="YES",IF(O15="Implemented","✅ Triggered+Mitigated",IF(O15="Partial","⚠️ Partial Controls","❌ Unmitigated")),"— Not Triggered") -> — Not Triggered | R15: IAM misconfigurations are endemic in cloud; automated analysis tools reveal paths human review misses
... A22: IT-VII-019 | B22: Stage VII – Risk & Impact Analysis | C22: M&A Due Diligence — Inherited Cyber Risk Materialization | D22: Acquiring organization inherits critical cyber vulnerabilities from acquired company that were not disclosed or discovered in due diligence, resulting in breach of combined entity post-merger | E22: Acquired Entity IT Environment | F22: Pre-existing vulnerabilities, malware, or backdoors in acquired environment | G22: Cybercriminal / Nation-State | H22: 3 | I22: 4 | J22: 12 | K22: HIGH | L22: Cyber due diligence as M&A requirement; network isolation of acquired entity post-close; security baseline assessment within 90 days; integration security roadmap | M22: NIST CSF ID.RA-1 / SEC Cybersecurity Rules | N22: CAPEC-167 | O22: None | P22: NO | Q22: =IF(P22="YES",IF(O22="Implemented","✅ Triggered+Mitigated",IF(O22="Partial","⚠️ Partial Controls","❌ Unmitigated")),"— Not Triggered") -> — Not Triggered | R22: Marriott's Starwood breach originated in systems acquired without cyber due diligence — $124M fine

Sheet 🔵 Shared Threats
A2: PASTA Threat Register — 🔵 Shared Threats
A3: Threat ID | B3: PASTA Stage | C3: Threat Scenario | D3: Threat Description | E3: Target Asset | F3: Attack Vector | G3: Threat Actor | H3: Likelihood (1-5) | I3: Impact (1-5) | J3: Risk Score | K3: Risk Level | L3: Control Mitigation | M3: Control Standard Ref | N3: Attack Pattern (CAPEC) | O3: Control Status | P3: Threat Triggered? | Q3: App Status | R3: Notes
A4: SH-I-001 | B4: Stage I – Business Objectives | C4: Business Continuity Disruption Across IT and OT | D4: Coordinated attack targets both IT business systems and OT process control simultaneously, exceeding organizational recovery capabilities and causing extended operational shutdown | E4: IT/OT Combined Operations | F4: Coordinated multi-vector attack leveraging both IT phishing and OT protocol exploitation | G4: Nation-State | H4: 2 | I4: 5 | J4: 10 | K4: HIGH | L4: Integrated IT/OT incident response plan; independent OT and IT recovery capability; tested cross-domain tabletop exercises; cyber crisis management team | M4: NIST CSF RC.RP-1 / IEC 62443-2-1 | N4: CAPEC-549 | O4: None | P4: NO | Q4: =IF(P4="YES",IF(O4="Implemented","✅ Triggered+Mitigated",IF(O4="Partial","⚠️ Partial Controls","❌ Unmitigated")),"— Not Triggered") -> — Not Triggered | R4: Most organizations prepare IT and OT resilience independently — integrated planning is the gap
A5: SH-II-002 | B5: Stage II – Technical Scope | C5: Dual-Homed Host as Cross-Domain Pivot | D5: Host with simultaneous connections to both IT and OT networks (historian, jump server, data aggregator) identified through network reconnaissance and used as cross-domain pivot point | E5: Dual-Homed Hosts / Historians | F5: Compromise of dual-homed host → OT network access | G5: Nation-State / Cybercriminal | H5: 4 | I5: 5 | J5: 20 | K5: CRITICAL | L5: Eliminate all dual-homed hosts; enforce strict network separation; where dual-homed is operationally required, apply enhanced monitoring and hardening | M5: IEC 62443-3-3 SR 5.1 / NIST SP 800-82 | N5: CAPEC-122 | O5: None | P5: NO | Q5: =IF(P5="YES",IF(O5="Implemented","✅ Triggered+Mitigated",IF(O5="Partial","⚠️ Partial Controls","❌ Unmitigated")),"— Not Triggered") -> — Not Triggered | R5: Dual-homed hosts are the most common IT-to-OT lateral movement enabler found in assessments
A6: SH-III-003 | B6: Stage III – App Decomposition | C6: Shared Authentication Infrastructure Compromise | D6: Identity infrastructure shared between IT and OT environments (shared Active Directory, RADIUS server) compromised, giving attacker authentication to both domains simultaneously | E6: Shared Active Directory / RADIUS | F6: AD domain compromise → OT authentication bypass | G6: Nation-State | H6: 3 | I6: 5 | J6: 15 | K6: HIGH | L6: Separate OT authentication infrastructure from IT AD; dedicated OT domain or local authentication; OT-specific PAM; monitor cross-domain authentication events | M6: IEC 62443-3-3 SR 1.1 / NIST SP 800-82 | N6: CAPEC-194 | O6: None | P6: NO | Q6: =IF(P6="YES",IF(O6="Implemented","✅ Triggered+Mitigated",IF(O6="Partial","⚠️ Partial Controls","❌ Unmitigated")),"— Not Triggered") -> — Not Triggered | R6: Shared AD between IT and OT is a systemic architectural risk — separation is the recommended control
A7: SH-IV-004 | B7: Stage IV – Threat Analysis | C7: Third-Party Vendor as Threat Vector (IT and OT) | D7: Trusted vendor with access to both IT and OT environments is compromised, providing attacker with legitimate credentials and access paths into both domains simultaneously | E7: Vendor Access / Third-Party Systems | F7: Vendor credential compromise; supply chain software compromise | G7: Nation-State / Cybercriminal | H7: 4 | I7: 5 | J7: 20 | K7: CRITICAL | L7: Vendor risk management program covering IT and OT access; JIT/JEA for all vendor access; MFA; session recording; continuous vendor monitoring; contract security requirements | M7: IEC 62443-2-4 / NIST SP 800-161 | N7: CAPEC-439 | O7: None | P7: NO | Q7: =IF(P7="YES",IF(O7="Implemented","✅ Triggered+Mitigated",IF(O7="Partial","⚠️ Partial Controls","❌ Unmitigated")),"— Not Triggered") -> — Not Triggered | R7: SolarWinds demonstrated the cascading impact of trusted vendor compromise — both IT and OT customers were affected
A8: SH-IV-005 | B8: Stage IV – Threat Analysis | C8: Coordinated Phishing Campaign Targeting OT and IT Staff | D8: Sophisticated spear-phishing campaign simultaneously targets IT administrators and OT engineers with role-specific lures, maximizing likelihood of at least one successful credential compromise | E8: IT and OT Personnel | F8: Targeted spear-phishing; credential harvesting; watering hole attacks | G8: Nation-State / Cybercriminal | H8: 4 | I8: 4 | J8: 16 | K8: HIGH | L8: Security awareness training tailored for both IT and OT roles; phishing simulation program; MFA on all accounts; email security gateway; OT-specific threat intelligence sharing | M8: IEC 62443-2-1 / NIST CSF PR.AT-1 | N8: CAPEC-98 | O8: None | P8: NO | Q8: =IF(P8="YES",IF(O8="Implemented","✅ Triggered+Mitigated",IF(O8="Partial","⚠️ Partial Controls","❌ Unmitigated")),"— Not Triggered") -> — Not Triggered | R8: Personnel are the common thread across IT and OT — training programs must address both contexts
A9: SH-V-006 | B9: Stage V – Vulnerability Analysis | C9: Unmonitored Cross-Domain Network Traffic | D9: Lack of network traffic visibility at the IT/OT boundary creates blind spots where attacker lateral movement, data exfiltration, or command-and-control traffic goes undetected for extended periods | E9: IT/OT Network Boundary | F9: Encrypted C2 traffic; protocol tunneling; legitimate protocol abuse | G9: Nation-State / Cybercriminal | H9: 4 | I9: 4 | J9: 16 | K9: HIGH | L9: Network Traffic Analysis (NTA) at IT/OT boundary; OT-aware NDR (Dragos, Claroty, Nozomi); SIEM correlation of IT and OT events; anomaly detection on cross-boundary flows | M9: IEC 62443-3-3 SR 6.2 / NIST SP 800-82 | N9: CAPEC-188 | O9: None | P9: NO | Q9: =IF(P9="YES",IF(O9="Implemented","✅ Triggered+Mitigated",IF(O9="Partial","⚠️ Partial Controls","❌ Unmitigated")),"— Not Triggered") -> — Not Triggered | R9: Unified visibility across IT and OT is the most common security gap identified in ICS assessments
A10: SH-VI-007 | B10: Stage VI – Attack Modeling | C10: Full Kill Chain: Phishing to Physical Impact | D10: End-to-end modeled attack: spear-phishing IT user → domain compromise → historian pivot → SCADA access → PLC manipulation → safety system bypass → physical process damage | E10: Enterprise IT → OT → Physical Process | F10: Multi-stage kill chain crossing IT/OT boundary | G10: Nation-State | H10: 2 | I10: 5 | J10: 10 | K10: HIGH | L10: Defense-in-depth at every kill chain stage; IT/OT segmentation as critical chokepoint; OT behavioral detection; independent physical safety systems; cyber-physical impact assessment | M10: IEC 62443-3-3 / NIST CSF | N10: CAPEC-439 | O10: None | P10: NO | Q10: =IF(P10="YES",IF(O10="Implemented","✅ Triggered+Mitigated",IF(O10="Partial","⚠️ Partial Controls","❌ Unmitigated")),"— Not Triggered") -> — Not Triggered | R10: This kill chain is documented in MITRE ATT&CK for ICS and has been executed in real-world incidents
A11: SH-VI-008 | B11: Stage VI – Attack Modeling | C11: Supply Chain Attack Propagating to IT and OT | D11: Compromised software update from shared vendor (SCADA vendor, IT security tool) deploys malware that propagates across both IT and OT environments simultaneously | E11: Software Supply Chain / IT and OT Systems | F11: Trojanized software update; build system compromise | G11: Nation-State | H11: 2 | I11: 5 | J11: 10 | K11: HIGH | L11: Separate update mechanisms for IT and OT; software signing verification; update staging and testing; network segmentation limiting blast radius; supply chain threat intelligence | M11: NIST SP 800-161 / IEC 62443-2-4 | N11: CAPEC-439 | O11: None | P11: NO | Q11: =IF(P11="YES",IF(O11="Implemented","✅ Triggered+Mitigated",IF(O11="Partial","⚠️ Partial Controls","❌ Unmitigated")),"— Not Triggered") -> — Not Triggered | R11: Kaseya VSA attack affected both IT and OT customers of MSPs — supply chain blast radius is difficult to scope
A12: SH-VII-009 | B12: Stage VII – Risk & Impact Analysis | C12: Cascading IT/OT Failure — Maximum Business Impact | D12: Worst-case risk scenario: simultaneous IT business system outage and OT process shutdown causes regulatory reporting failure, environmental release, financial losses, and reputational damage | E12: Enterprise-Wide IT and OT | F12: Coordinated multi-domain attack or cascading failure from single entry point | G12: Nation-State | H12: 2 | I12: 5 | J12: 10 | K12: HIGH | L12: Enterprise risk quantification (FAIR model); integrated BCP/DRP covering IT and OT; crisis communication plan; regulatory notification procedures; board-level cyber risk reporting | M12: IEC 62443-2-1 / NIST CSF ID.RA-4 | N12: CAPEC-549 | O12: None | P12: NO | Q12: =IF(P12="YES",IF(O12="Implemented","✅ Triggered+Mitigated",IF(O12="Partial","⚠️ Partial Controls","❌ Unmitigated")),"— Not Triggered") -> — Not Triggered | R12: PASTA Stage VII explicitly requires business impact quantification — FAIR model recommended for financial risk expression
A13: SH-VII-010 | B13: Stage VII – Risk & Impact Analysis | C13: Cyber Insurance Coverage Gap — Uninsured OT Losses | D13: Cyber insurance policy exclusions (war exclusion, infrastructure exclusion, unencrypted data) result in OT-related cyber losses being uncovered, creating unbudgeted financial exposure | E13: Cyber Insurance Policy / Financial Risk | F13: Any covered cyber incident triggering policy exclusion | G13: Nation-State / Cybercriminal | H13: 3 | I13: 4 | J13: 12 | K13: HIGH | L13: Annual cyber insurance coverage review with OT-specific scenarios; legal review of exclusion clauses; supplement with property and business interruption coverage; quantify uninsured exposure | M13: NIST CSF ID.RA-4 / FAIR Model | N13: CAPEC-N/A | O13: None | P13: NO | Q13: =IF(P13="YES",IF(O13="Implemented","✅ Triggered+Mitigated",IF(O13="Partial","⚠️ Partial Controls","❌ Unmitigated")),"— Not Triggered") -> — Not Triggered | R13: Lloyd's attribution-based war exclusion and infrastructure exclusion clauses are actively litigated — legal review is essential
